{
  "required": true,
  "compatibilityLevel": "JAVA_8",
  "package": "com.salhack.summit.mixin.client",
  "refmap": "mixins.summit.refmap.json",
  "mixins": [
    "MixinAbstractClientPlayer",
    "MixinAbstractHorse",
    "MixinActiveRenderInfo",
    "MixinBufferBuilder",
    "MixinChunk",
    "MixinDebugRendererChunkBorder",
    "MixinGuiBossOverlay",
    "MixinGuiDisconnected",
    "MixinGuiIngame",
    "MixinGuiMainMenu",
    "MixinGuiNewChat",
    "MixinGuiScreen",
    "MixinItemBlock",
    "MixinItemRenderer",
    "MixinLayerArmorBase",
    "MixinMapItemRenderer",
    "MixinMinecraft",
    "MixinModelPlayer",
    "MixinNetHandlerPlayClient",
    "MixinNetworkManager",
    "MixinParticleManager",
    "MixinPlayerControllerMP",
    "MixinRenderEntityItem",
    "MixinRenderer",
    "MixinRendererLivingEntity",
    "MixinRenderManager",
    "MixinRenderPlayer",
    "MixinTileEntityRendererDispatcher",
    "MixinVisGraph",
    "MixinWorld",
    "blocks.MixinBlock",
    "blocks.MixinBlockAir",
    "blocks.MixinBlockBeacon",
    "blocks.MixinBlockBed",
    "blocks.MixinBlockBrewingStand",
    "blocks.MixinBlockBush",
    "blocks.MixinBlockCactus",
    "blocks.MixinBlockCake",
    "blocks.MixinBlockChorusFlower",
    "blocks.MixinBlockChorusPlant",
    "blocks.MixinBlockCocoa",
    "blocks.MixinBlockDoor",
    "blocks.MixinBlockEndRod",
    "blocks.MixinBlockFire",
    "blocks.MixinBlockFlowerPot",
    "blocks.MixinBlockGrass",
    "blocks.MixinBlockHopper",
    "blocks.MixinBlockIce",
    "blocks.MixinBlockLadder",
    "blocks.MixinBlockLeaves",
    "blocks.MixinBlockLiquid",
    "blocks.MixinBlockMobSpawner",
    "blocks.MixinBlockPane",
    "blocks.MixinBlockPortal",
    "blocks.MixinBlockRailBase",
    "blocks.MixinBlockRedstoneDiode",
    "blocks.MixinBlockRedstoneWire",
    "blocks.MixinBlockReed",
    "blocks.MixinBlockSlime",
    "blocks.MixinBlockStainedGlass",
    "blocks.MixinBlockStainedGlassPane",
    "blocks.MixinBlockStairs",
    "blocks.MixinBlockStructureVoid",
    "blocks.MixinBlockTorch",
    "blocks.MixinBlockTrapDoor",
    "blocks.MixinBlockTripWire",
    "blocks.MixinBlockTripWireHook",
    "blocks.MixinBlockVine",
    "blocks.MixinBlockWeb",
    "entity.MixinEntity",
    "entity.MixinEntityLivingBase",
    "entity.MixinEntityLlama",
    "entity.MixinEntityPig",
    "entity.MixinEntityPlayer",
    "entity.MixinEntityPlayerSP",
    "entity.MixinEntityRenderer"
  ],
  "client": [
    "MixinMovementInputFromOptions"
  ]
}